aerosim_drone/__init__.py
aerosim_drone/drone.py
aerosim_drone-0.1.2.dist-info/METADATA
aerosim_drone-0.1.2.dist-info/WHEEL
aerosim_drone-0.1.2.dist-info/top_level.txt
aerosim_drone-0.1.2.dist-info/RECORD
