Metadata-Version: 2.4
Name: aerosim_drone
Version: 0.1.2
Summary: WebSocket drone client for AeroSim
Author: aerosim
License: MIT
Requires-Python: >=3.9
Requires-Dist: websockets
Requires-Dist: asyncio
